raspirri/__init__.py
raspirri/main_app.py
raspirri/main_watchdog.py
raspirri/ble/__init__.py
raspirri/ble/advertisement.py
raspirri/ble/bletools.py
raspirri/ble/common.py
raspirri/ble/exceptions.py
raspirri/ble/service.py
raspirri/ble/wifi.py
raspirri/server/__init__.py
raspirri/server/const.py
raspirri/server/exceptions.py
raspirri/server/helpers.py
raspirri/server/mqtt.py
raspirri/server/services.py
raspirri_server-1.0.7.dist-info/LICENSE.md
raspirri_server-1.0.7.dist-info/METADATA
raspirri_server-1.0.7.dist-info/WHEEL
raspirri_server-1.0.7.dist-info/top_level.txt
raspirri_server-1.0.7.dist-info/RECORD
