Metadata-Version: 2.1
Name: raspirri-server
Version: 1.0.7
Summary: RaspirriV1 Server
Author: Marios Karagiannopoulos
Author-email: mariosk@gmail.com
License: MIT
License-File: LICENSE.md
Requires-Dist: fastapi[all] ==0.104.1
Requires-Dist: RPi.GPIO ==0.7.1
Requires-Dist: future ==0.18.2
Requires-Dist: paho-mqtt ==1.6.1
Requires-Dist: getmac ==0.8.3
Requires-Dist: distro ==1.7.0
Requires-Dist: lockfile ==0.12.2
Requires-Dist: APScheduler ==3.9.1
Requires-Dist: Deprecated ==1.2.13
Requires-Dist: requests ==2.27.1
Requires-Dist: subprocess.run ==0.0.8
Requires-Dist: dbus-python ==1.3.2
Requires-Dist: PyGObject ==3.46.0
Requires-Dist: pytest ==7.4.3
Requires-Dist: pytest-mock ==3.12.0
Requires-Dist: pytest-ordering ==0.6
Requires-Dist: loguru ==0.7.2
Requires-Dist: pytest-asyncio ==0.21.1
Requires-Dist: coverage ==7.3.2
Requires-Dist: uvicorn ==0.27.0
